tests/__init__.py
tests/test_generate_class_diagram.py
umlfy/__init__.py
umlfy/class_diagram.py
umlify-0.1.dist-info/LICENSE
umlify-0.1.dist-info/METADATA
umlify-0.1.dist-info/WHEEL
umlify-0.1.dist-info/top_level.txt
umlify-0.1.dist-info/RECORD
