Metadata-Version: 2.1
Name: umlify
Version: 0.1
Summary: A Python library to generate plantUML diagrams from code.
Home-page: https://github.com/adelinesharla/UMLfy
Author: Adeline Sharla
Author-email: adelinesharla@duck.com
License: MIT
Classifier: Programming Language :: Python :: 3
Classifier: License :: OSI Approved :: MIT License
License-File: LICENSE
